regi/__init__.py
regi/regi.py
regi-3.0.dist-info/LICENCE.txt
regi-3.0.dist-info/METADATA
regi-3.0.dist-info/WHEEL
regi-3.0.dist-info/top_level.txt
regi-3.0.dist-info/RECORD
